specderiv/__init__.py
specderiv/specderiv.py
spectral_derivatives-0.10.dist-info/licenses/LICENSE
spectral_derivatives-0.10.dist-info/METADATA
spectral_derivatives-0.10.dist-info/WHEEL
spectral_derivatives-0.10.dist-info/top_level.txt
spectral_derivatives-0.10.dist-info/RECORD
