Metadata-Version: 2.4
Name: spectral-derivatives
Version: 0.10
Summary: Functions to take spectral derivatives with the Chebyshev and Fourier bases
Author-email: Pavel Komarov <pvlkmrv@gmail.com>
License: BSD License
Project-URL: Documentation, https://pavelkomarov.com/spectral-derivatives
Project-URL: Repository, https://github.com/pavelkomarov/spectral-derivatives
License-File: LICENSE
Requires-Dist: pytest
Requires-Dist: numpy
Requires-Dist: scipy
Requires-Dist: matplotlib
Dynamic: license-file
